{
    "all_stats": {
        "num_courses": 329, 
        "num_departments": 57
    }, 
    "departments": [
        {
            "abbr": "ACCOUNTANCY", 
            "courses": [
                {
                    "code": "ACCOUNTANCY 201", 
                    "course_url": "http://www.chegg.com/courses/1586071/ACCOUNTANCY/201", 
                    "name": "Accounting Principles I"
                }, 
                {
                    "code": "ACCOUNTANCY 202", 
                    "course_url": "http://www.chegg.com/courses/1586071/ACCOUNTANCY/202", 
                    "name": "Accounting Principles II"
                }, 
                {
                    "code": "ACCOUNTANCY 250", 
                    "course_url": "http://www.chegg.com/courses/1586071/ACCOUNTANCY/250", 
                    "name": "Microcomputer Applications For Business"
                }
            ], 
            "name": "", 
            "url": "http://www.chegg.com/courses/1586071/ACCOUNTANCY"
        }, 
        {
            "abbr": "ANTHROPOLOGY", 
            "courses": [
                {
                    "code": "ANTHROPOLOGY 150", 
                    "course_url": "http://www.chegg.com/courses/1586071/ANTHROPOLOGY/150", 
                    "name": "Cultural Anthropology"
                }, 
                {
                    "code": "ANTHROPOLOGY 151", 
                    "course_url": "http://www.chegg.com/courses/1586071/ANTHROPOLOGY/151", 
                    "name": "Human Evolution"
                }, 
                {
                    "code": "ANTHROPOLOGY 251", 
                    "course_url": "http://www.chegg.com/courses/1586071/ANTHROPOLOGY/251", 
                    "name": "Human Diversity"
                }
            ], 
            "name": "Anthropology", 
            "url": "http://www.chegg.com/courses/1586071/ANTHROPOLOGY"
        }, 
        {
            "abbr": "ART", 
            "courses": [
                {
                    "code": "ART 131", 
                    "course_url": "http://www.chegg.com/courses/1586071/ART/131", 
                    "name": "Foundation Drawing"
                }, 
                {
                    "code": "ART 210", 
                    "course_url": "http://www.chegg.com/courses/1586071/ART/210", 
                    "name": "Visual Arts Awareness"
                }, 
                {
                    "code": "ART 274", 
                    "course_url": "http://www.chegg.com/courses/1586071/ART/274", 
                    "name": "Photography I For Non- Art Majors"
                }, 
                {
                    "code": "ART 275", 
                    "course_url": "http://www.chegg.com/courses/1586071/ART/275", 
                    "name": "Introduction to Photography"
                }
            ], 
            "name": "Art", 
            "url": "http://www.chegg.com/courses/1586071/ART"
        }, 
        {
            "abbr": "BIOLOGY", 
            "courses": [
                {
                    "code": "BIOLOGY 100", 
                    "course_url": "http://www.chegg.com/courses/1586071/BIOLOGY/100", 
                    "name": "Introduction to Botany"
                }, 
                {
                    "code": "BIOLOGY 101", 
                    "course_url": "http://www.chegg.com/courses/1586071/BIOLOGY/101", 
                    "name": "Introduction to Zoology"
                }, 
                {
                    "code": "BIOLOGY 103", 
                    "course_url": "http://www.chegg.com/courses/1586071/BIOLOGY/103", 
                    "name": "Natural Science: Biology"
                }, 
                {
                    "code": "BIOLOGY 108", 
                    "course_url": "http://www.chegg.com/courses/1586071/BIOLOGY/108", 
                    "name": "Introduction to Biological Aging"
                }, 
                {
                    "code": "BIOLOGY 111", 
                    "course_url": "http://www.chegg.com/courses/1586071/BIOLOGY/111", 
                    "name": "Principles of Biology I"
                }, 
                {
                    "code": "BIOLOGY 112", 
                    "course_url": "http://www.chegg.com/courses/1586071/BIOLOGY/112", 
                    "name": "Principles of Biology II"
                }, 
                {
                    "code": "BIOLOGY 130", 
                    "course_url": "http://www.chegg.com/courses/1586071/BIOLOGY/130", 
                    "name": "Principles of Microbiology"
                }, 
                {
                    "code": "BIOLOGY 200", 
                    "course_url": "http://www.chegg.com/courses/1586071/BIOLOGY/200", 
                    "name": "Human Anatomy And Physiology I"
                }, 
                {
                    "code": "BIOLOGY 201", 
                    "course_url": "http://www.chegg.com/courses/1586071/BIOLOGY/201", 
                    "name": "Human Anatomy And Physiology Lab I"
                }, 
                {
                    "code": "BIOLOGY 202", 
                    "course_url": "http://www.chegg.com/courses/1586071/BIOLOGY/202", 
                    "name": "Human Anatomy And Physiology II"
                }, 
                {
                    "code": "BIOLOGY 203", 
                    "course_url": "http://www.chegg.com/courses/1586071/BIOLOGY/203", 
                    "name": "Human Anatomy And Physiology Lab II"
                }, 
                {
                    "code": "BIOLOGY 211", 
                    "course_url": "http://www.chegg.com/courses/1586071/BIOLOGY/211", 
                    "name": "General Genetics"
                }, 
                {
                    "code": "BIOLOGY 212", 
                    "course_url": "http://www.chegg.com/courses/1586071/BIOLOGY/212", 
                    "name": "General Genetics Laboratory"
                }, 
                {
                    "code": "BIOLOGY 217", 
                    "course_url": "http://www.chegg.com/courses/1586071/BIOLOGY/217", 
                    "name": "General Ecology"
                }, 
                {
                    "code": "BIOLOGY 265", 
                    "course_url": "http://www.chegg.com/courses/1586071/BIOLOGY/265", 
                    "name": "Introductory Human Physiology"
                }
            ], 
            "name": "Biology", 
            "url": "http://www.chegg.com/courses/1586071/BIOLOGY"
        }, 
        {
            "abbr": "BUSINESS MANAGEMENT TECHNOLOGY", 
            "courses": [
                {
                    "code": "BUSINESS MANAGEMENT TECHNOLOGY 103", 
                    "course_url": "http://www.chegg.com/courses/1586071/BUSINESS%20MANAGEMENT%20TECHNOLOGY/103", 
                    "name": "Essentials of Management Technology"
                }, 
                {
                    "code": "BUSINESS MANAGEMENT TECHNOLOGY 104", 
                    "course_url": "http://www.chegg.com/courses/1586071/BUSINESS%20MANAGEMENT%20TECHNOLOGY/104", 
                    "name": "Introduction to Business in The Global Environment"
                }, 
                {
                    "code": "BUSINESS MANAGEMENT TECHNOLOGY 170", 
                    "course_url": "http://www.chegg.com/courses/1586071/BUSINESS%20MANAGEMENT%20TECHNOLOGY/170", 
                    "name": "Applied Mathematics For Business"
                }, 
                {
                    "code": "BUSINESS MANAGEMENT TECHNOLOGY 202", 
                    "course_url": "http://www.chegg.com/courses/1586071/BUSINESS%20MANAGEMENT%20TECHNOLOGY/202", 
                    "name": "Elements of Human Resource Management"
                }, 
                {
                    "code": "BUSINESS MANAGEMENT TECHNOLOGY 211", 
                    "course_url": "http://www.chegg.com/courses/1586071/BUSINESS%20MANAGEMENT%20TECHNOLOGY/211", 
                    "name": "Basic Accounting I"
                }, 
                {
                    "code": "BUSINESS MANAGEMENT TECHNOLOGY 212", 
                    "course_url": "http://www.chegg.com/courses/1586071/BUSINESS%20MANAGEMENT%20TECHNOLOGY/212", 
                    "name": "Basic Accounting II"
                }, 
                {
                    "code": "BUSINESS MANAGEMENT TECHNOLOGY 213", 
                    "course_url": "http://www.chegg.com/courses/1586071/BUSINESS%20MANAGEMENT%20TECHNOLOGY/213", 
                    "name": "Essentials of Management Accounting"
                }, 
                {
                    "code": "BUSINESS MANAGEMENT TECHNOLOGY 214", 
                    "course_url": "http://www.chegg.com/courses/1586071/BUSINESS%20MANAGEMENT%20TECHNOLOGY/214", 
                    "name": "Essentials of Intermediate Accounting"
                }, 
                {
                    "code": "BUSINESS MANAGEMENT TECHNOLOGY 216", 
                    "course_url": "http://www.chegg.com/courses/1586071/BUSINESS%20MANAGEMENT%20TECHNOLOGY/216", 
                    "name": "Survey of Cost Accounting"
                }, 
                {
                    "code": "BUSINESS MANAGEMENT TECHNOLOGY 217", 
                    "course_url": "http://www.chegg.com/courses/1586071/BUSINESS%20MANAGEMENT%20TECHNOLOGY/217", 
                    "name": "Survey of Taxation"
                }, 
                {
                    "code": "BUSINESS MANAGEMENT TECHNOLOGY 218", 
                    "course_url": "http://www.chegg.com/courses/1586071/BUSINESS%20MANAGEMENT%20TECHNOLOGY/218", 
                    "name": "Automated Bookkeeping"
                }, 
                {
                    "code": "BUSINESS MANAGEMENT TECHNOLOGY 219", 
                    "course_url": "http://www.chegg.com/courses/1586071/BUSINESS%20MANAGEMENT%20TECHNOLOGY/219", 
                    "name": "Business Accounting Projects"
                }, 
                {
                    "code": "BUSINESS MANAGEMENT TECHNOLOGY 243", 
                    "course_url": "http://www.chegg.com/courses/1586071/BUSINESS%20MANAGEMENT%20TECHNOLOGY/243", 
                    "name": "Survey in Finance"
                }, 
                {
                    "code": "BUSINESS MANAGEMENT TECHNOLOGY 245", 
                    "course_url": "http://www.chegg.com/courses/1586071/BUSINESS%20MANAGEMENT%20TECHNOLOGY/245", 
                    "name": "Business Management Accounting Internship"
                }, 
                {
                    "code": "BUSINESS MANAGEMENT TECHNOLOGY 246", 
                    "course_url": "http://www.chegg.com/courses/1586071/BUSINESS%20MANAGEMENT%20TECHNOLOGY/246", 
                    "name": "Business Management Internship"
                }, 
                {
                    "code": "BUSINESS MANAGEMENT TECHNOLOGY 250", 
                    "course_url": "http://www.chegg.com/courses/1586071/BUSINESS%20MANAGEMENT%20TECHNOLOGY/250", 
                    "name": "Problems in Business Management"
                }, 
                {
                    "code": "BUSINESS MANAGEMENT TECHNOLOGY 280", 
                    "course_url": "http://www.chegg.com/courses/1586071/BUSINESS%20MANAGEMENT%20TECHNOLOGY/280", 
                    "name": "Essentials of Business Law"
                }, 
                {
                    "code": "BUSINESS MANAGEMENT TECHNOLOGY 290", 
                    "course_url": "http://www.chegg.com/courses/1586071/BUSINESS%20MANAGEMENT%20TECHNOLOGY/290", 
                    "name": "Special Topics: Business Management Technology"
                }
            ], 
            "name": "", 
            "url": "http://www.chegg.com/courses/1586071/BUSINESS%20MANAGEMENT%20TECHNOLOGY"
        }, 
        {
            "abbr": "CHEMISTRY", 
            "courses": [
                {
                    "code": "CHEMISTRY 100", 
                    "course_url": "http://www.chegg.com/courses/1586071/CHEMISTRY/100", 
                    "name": "Chemistry And Society"
                }, 
                {
                    "code": "CHEMISTRY 101", 
                    "course_url": "http://www.chegg.com/courses/1586071/CHEMISTRY/101", 
                    "name": "Chemistry For Everyone"
                }, 
                {
                    "code": "CHEMISTRY 110", 
                    "course_url": "http://www.chegg.com/courses/1586071/CHEMISTRY/110", 
                    "name": "Introduction to General, Organic, And Biochemistry I"
                }, 
                {
                    "code": "CHEMISTRY 111", 
                    "course_url": "http://www.chegg.com/courses/1586071/CHEMISTRY/111", 
                    "name": "Introduction to General, Organic, And Biochemistry Laboratory I"
                }, 
                {
                    "code": "CHEMISTRY 112", 
                    "course_url": "http://www.chegg.com/courses/1586071/CHEMISTRY/112", 
                    "name": "Introduction to General, Organic, And Biochemistry II"
                }, 
                {
                    "code": "CHEMISTRY 113", 
                    "course_url": "http://www.chegg.com/courses/1586071/CHEMISTRY/113", 
                    "name": "Introduction to General, Organic, And Biochemistry Laboratory II"
                }, 
                {
                    "code": "CHEMISTRY 151", 
                    "course_url": "http://www.chegg.com/courses/1586071/CHEMISTRY/151", 
                    "name": "Principles of Chemistry I"
                }, 
                {
                    "code": "CHEMISTRY 152", 
                    "course_url": "http://www.chegg.com/courses/1586071/CHEMISTRY/152", 
                    "name": "Principles of Chemistry I Laboratory"
                }, 
                {
                    "code": "CHEMISTRY 153", 
                    "course_url": "http://www.chegg.com/courses/1586071/CHEMISTRY/153", 
                    "name": "Principles of Chemistry II"
                }, 
                {
                    "code": "CHEMISTRY 154", 
                    "course_url": "http://www.chegg.com/courses/1586071/CHEMISTRY/154", 
                    "name": "Qualitative Analysis"
                }, 
                {
                    "code": "CHEMISTRY 164", 
                    "course_url": "http://www.chegg.com/courses/1586071/CHEMISTRY/164", 
                    "name": "Technical Physics: Heat And Light"
                }, 
                {
                    "code": "CHEMISTRY 263 ,4", 
                    "course_url": "http://www.chegg.com/courses/1586071/CHEMISTRY/263%20%2C4", 
                    "name": "Organic Chemistry Lecture I, II"
                }, 
                {
                    "code": "CHEMISTRY 265 ,6", 
                    "course_url": "http://www.chegg.com/courses/1586071/CHEMISTRY/265%20%2C6", 
                    "name": "Organic Chemistry Lab I, II"
                }
            ], 
            "name": "Chemistry", 
            "url": "http://www.chegg.com/courses/1586071/CHEMISTRY"
        }, 
        {
            "abbr": "CIVIL ENGINEERING", 
            "courses": [
                {
                    "code": "CIVIL ENGINEERING 201", 
                    "course_url": "http://www.chegg.com/courses/1586071/CIVIL%20ENGINEERING/201", 
                    "name": "Statics"
                }, 
                {
                    "code": "CIVIL ENGINEERING 202", 
                    "course_url": "http://www.chegg.com/courses/1586071/CIVIL%20ENGINEERING/202", 
                    "name": "Introduction to The Mechanics of Solids"
                }
            ], 
            "name": "", 
            "url": "http://www.chegg.com/courses/1586071/CIVIL%20ENGINEERING"
        }, 
        {
            "abbr": "COMMUNICATION", 
            "courses": [
                {
                    "code": "COMMUNICATION 102", 
                    "course_url": "http://www.chegg.com/courses/1586071/COMMUNICATION/102", 
                    "name": "Survey of Mass Communication"
                }, 
                {
                    "code": "COMMUNICATION 105", 
                    "course_url": "http://www.chegg.com/courses/1586071/COMMUNICATION/105", 
                    "name": "Introduction to Public Speaking"
                }, 
                {
                    "code": "COMMUNICATION 106", 
                    "course_url": "http://www.chegg.com/courses/1586071/COMMUNICATION/106", 
                    "name": "Effective Oral Communication"
                }, 
                {
                    "code": "COMMUNICATION 115", 
                    "course_url": "http://www.chegg.com/courses/1586071/COMMUNICATION/115", 
                    "name": "Survey of Communication Theory"
                }, 
                {
                    "code": "COMMUNICATION 225", 
                    "course_url": "http://www.chegg.com/courses/1586071/COMMUNICATION/225", 
                    "name": "Listening"
                }, 
                {
                    "code": "COMMUNICATION 226", 
                    "course_url": "http://www.chegg.com/courses/1586071/COMMUNICATION/226", 
                    "name": "Interviewing"
                }, 
                {
                    "code": "COMMUNICATION 227", 
                    "course_url": "http://www.chegg.com/courses/1586071/COMMUNICATION/227", 
                    "name": "Nonverbal Communication"
                }, 
                {
                    "code": "COMMUNICATION 235", 
                    "course_url": "http://www.chegg.com/courses/1586071/COMMUNICATION/235", 
                    "name": "Interpersonal Communication"
                }, 
                {
                    "code": "COMMUNICATION 245", 
                    "course_url": "http://www.chegg.com/courses/1586071/COMMUNICATION/245", 
                    "name": "Argumentation"
                }
            ], 
            "name": "", 
            "url": "http://www.chegg.com/courses/1586071/COMMUNICATION"
        }, 
        {
            "abbr": "COMPUTER INFORMATION SYSTEMS", 
            "courses": [
                {
                    "code": "COMPUTER INFORMATION SYSTEMS 105", 
                    "course_url": "http://www.chegg.com/courses/1586071/COMPUTER%20INFORMATION%20SYSTEMS/105", 
                    "name": "Introduction to Computers And Application Software"
                }, 
                {
                    "code": "COMPUTER INFORMATION SYSTEMS 121", 
                    "course_url": "http://www.chegg.com/courses/1586071/COMPUTER%20INFORMATION%20SYSTEMS/121", 
                    "name": "Introduction to Logic/ Programming"
                }, 
                {
                    "code": "COMPUTER INFORMATION SYSTEMS 125", 
                    "course_url": "http://www.chegg.com/courses/1586071/COMPUTER%20INFORMATION%20SYSTEMS/125", 
                    "name": "Spreadsheet Software"
                }, 
                {
                    "code": "COMPUTER INFORMATION SYSTEMS 140", 
                    "course_url": "http://www.chegg.com/courses/1586071/COMPUTER%20INFORMATION%20SYSTEMS/140", 
                    "name": "Internet Tools"
                }, 
                {
                    "code": "COMPUTER INFORMATION SYSTEMS 141", 
                    "course_url": "http://www.chegg.com/courses/1586071/COMPUTER%20INFORMATION%20SYSTEMS/141", 
                    "name": "Web Site Administration"
                }, 
                {
                    "code": "COMPUTER INFORMATION SYSTEMS 145", 
                    "course_url": "http://www.chegg.com/courses/1586071/COMPUTER%20INFORMATION%20SYSTEMS/145", 
                    "name": "Operating Systems"
                }, 
                {
                    "code": "COMPUTER INFORMATION SYSTEMS 160", 
                    "course_url": "http://www.chegg.com/courses/1586071/COMPUTER%20INFORMATION%20SYSTEMS/160", 
                    "name": "Java Programming"
                }, 
                {
                    "code": "COMPUTER INFORMATION SYSTEMS 170", 
                    "course_url": "http://www.chegg.com/courses/1586071/COMPUTER%20INFORMATION%20SYSTEMS/170", 
                    "name": "Visual Basic"
                }, 
                {
                    "code": "COMPUTER INFORMATION SYSTEMS 212", 
                    "course_url": "http://www.chegg.com/courses/1586071/COMPUTER%20INFORMATION%20SYSTEMS/212", 
                    "name": "Multimedia And Interactive Web Elements"
                }, 
                {
                    "code": "COMPUTER INFORMATION SYSTEMS 245", 
                    "course_url": "http://www.chegg.com/courses/1586071/COMPUTER%20INFORMATION%20SYSTEMS/245", 
                    "name": "Introduction to Databases For Micros"
                }, 
                {
                    "code": "COMPUTER INFORMATION SYSTEMS 247", 
                    "course_url": "http://www.chegg.com/courses/1586071/COMPUTER%20INFORMATION%20SYSTEMS/247", 
                    "name": "Hardware Support"
                }, 
                {
                    "code": "COMPUTER INFORMATION SYSTEMS 256", 
                    "course_url": "http://www.chegg.com/courses/1586071/COMPUTER%20INFORMATION%20SYSTEMS/256", 
                    "name": "C++ Programming"
                }, 
                {
                    "code": "COMPUTER INFORMATION SYSTEMS 290", 
                    "course_url": "http://www.chegg.com/courses/1586071/COMPUTER%20INFORMATION%20SYSTEMS/290", 
                    "name": "Special Topics: Data Processing"
                }
            ], 
            "name": "", 
            "url": "http://www.chegg.com/courses/1586071/COMPUTER%20INFORMATION%20SYSTEMS"
        }, 
        {
            "abbr": "COMPUTER NETWORK ENGINEERING TECHNOLOGY", 
            "courses": [
                {
                    "code": "COMPUTER NETWORK ENGINEERING TECHNOLOGY 100", 
                    "course_url": "http://www.chegg.com/courses/1586071/COMPUTER%20NETWORK%20ENGINEERING%20TECHNOLOGY/100", 
                    "name": "Basic Electronics For Technicians"
                }, 
                {
                    "code": "COMPUTER NETWORK ENGINEERING TECHNOLOGY 125", 
                    "course_url": "http://www.chegg.com/courses/1586071/COMPUTER%20NETWORK%20ENGINEERING%20TECHNOLOGY/125", 
                    "name": "Digital Electronics For Technicians"
                }, 
                {
                    "code": "COMPUTER NETWORK ENGINEERING TECHNOLOGY 160", 
                    "course_url": "http://www.chegg.com/courses/1586071/COMPUTER%20NETWORK%20ENGINEERING%20TECHNOLOGY/160", 
                    "name": "Personal Computer Servicing"
                }, 
                {
                    "code": "COMPUTER NETWORK ENGINEERING TECHNOLOGY 180", 
                    "course_url": "http://www.chegg.com/courses/1586071/COMPUTER%20NETWORK%20ENGINEERING%20TECHNOLOGY/180", 
                    "name": "Microprocessor Service Practicum"
                }, 
                {
                    "code": "COMPUTER NETWORK ENGINEERING TECHNOLOGY 185", 
                    "course_url": "http://www.chegg.com/courses/1586071/COMPUTER%20NETWORK%20ENGINEERING%20TECHNOLOGY/185", 
                    "name": "Microprocessor Service Practicum Seminar"
                }, 
                {
                    "code": "COMPUTER NETWORK ENGINEERING TECHNOLOGY 240", 
                    "course_url": "http://www.chegg.com/courses/1586071/COMPUTER%20NETWORK%20ENGINEERING%20TECHNOLOGY/240", 
                    "name": "Microsoft Networking I"
                }, 
                {
                    "code": "COMPUTER NETWORK ENGINEERING TECHNOLOGY 242", 
                    "course_url": "http://www.chegg.com/courses/1586071/COMPUTER%20NETWORK%20ENGINEERING%20TECHNOLOGY/242", 
                    "name": "Microsoft Networking II"
                }, 
                {
                    "code": "COMPUTER NETWORK ENGINEERING TECHNOLOGY 244", 
                    "course_url": "http://www.chegg.com/courses/1586071/COMPUTER%20NETWORK%20ENGINEERING%20TECHNOLOGY/244", 
                    "name": "Microsoft Networking III"
                }, 
                {
                    "code": "COMPUTER NETWORK ENGINEERING TECHNOLOGY 246", 
                    "course_url": "http://www.chegg.com/courses/1586071/COMPUTER%20NETWORK%20ENGINEERING%20TECHNOLOGY/246", 
                    "name": "Microsoft Networking IV"
                }, 
                {
                    "code": "COMPUTER NETWORK ENGINEERING TECHNOLOGY 252", 
                    "course_url": "http://www.chegg.com/courses/1586071/COMPUTER%20NETWORK%20ENGINEERING%20TECHNOLOGY/252", 
                    "name": "Microsoft Networking V"
                }, 
                {
                    "code": "COMPUTER NETWORK ENGINEERING TECHNOLOGY 254", 
                    "course_url": "http://www.chegg.com/courses/1586071/COMPUTER%20NETWORK%20ENGINEERING%20TECHNOLOGY/254", 
                    "name": "Microsoft Networking VI"
                }, 
                {
                    "code": "COMPUTER NETWORK ENGINEERING TECHNOLOGY 256", 
                    "course_url": "http://www.chegg.com/courses/1586071/COMPUTER%20NETWORK%20ENGINEERING%20TECHNOLOGY/256", 
                    "name": "Microsoft Networking VII"
                }, 
                {
                    "code": "COMPUTER NETWORK ENGINEERING TECHNOLOGY 261", 
                    "course_url": "http://www.chegg.com/courses/1586071/COMPUTER%20NETWORK%20ENGINEERING%20TECHNOLOGY/261", 
                    "name": "Network Security"
                }, 
                {
                    "code": "COMPUTER NETWORK ENGINEERING TECHNOLOGY 262", 
                    "course_url": "http://www.chegg.com/courses/1586071/COMPUTER%20NETWORK%20ENGINEERING%20TECHNOLOGY/262", 
                    "name": "Linux Networking"
                }, 
                {
                    "code": "COMPUTER NETWORK ENGINEERING TECHNOLOGY 270", 
                    "course_url": "http://www.chegg.com/courses/1586071/COMPUTER%20NETWORK%20ENGINEERING%20TECHNOLOGY/270", 
                    "name": "Introduction to Network Technologies"
                }, 
                {
                    "code": "COMPUTER NETWORK ENGINEERING TECHNOLOGY 272", 
                    "course_url": "http://www.chegg.com/courses/1586071/COMPUTER%20NETWORK%20ENGINEERING%20TECHNOLOGY/272", 
                    "name": "Novell Networking I"
                }, 
                {
                    "code": "COMPUTER NETWORK ENGINEERING TECHNOLOGY 274", 
                    "course_url": "http://www.chegg.com/courses/1586071/COMPUTER%20NETWORK%20ENGINEERING%20TECHNOLOGY/274", 
                    "name": "Novell Networking II"
                }, 
                {
                    "code": "COMPUTER NETWORK ENGINEERING TECHNOLOGY 276", 
                    "course_url": "http://www.chegg.com/courses/1586071/COMPUTER%20NETWORK%20ENGINEERING%20TECHNOLOGY/276", 
                    "name": "Novell Networking III"
                }, 
                {
                    "code": "COMPUTER NETWORK ENGINEERING TECHNOLOGY 278", 
                    "course_url": "http://www.chegg.com/courses/1586071/COMPUTER%20NETWORK%20ENGINEERING%20TECHNOLOGY/278", 
                    "name": "Novell Networking IV"
                }, 
                {
                    "code": "COMPUTER NETWORK ENGINEERING TECHNOLOGY 280", 
                    "course_url": "http://www.chegg.com/courses/1586071/COMPUTER%20NETWORK%20ENGINEERING%20TECHNOLOGY/280", 
                    "name": "Field Experience in Microprocessor Service"
                }, 
                {
                    "code": "COMPUTER NETWORK ENGINEERING TECHNOLOGY 282", 
                    "course_url": "http://www.chegg.com/courses/1586071/COMPUTER%20NETWORK%20ENGINEERING%20TECHNOLOGY/282", 
                    "name": "Novell Networking V"
                }, 
                {
                    "code": "COMPUTER NETWORK ENGINEERING TECHNOLOGY 284", 
                    "course_url": "http://www.chegg.com/courses/1586071/COMPUTER%20NETWORK%20ENGINEERING%20TECHNOLOGY/284", 
                    "name": "Working With Tcp/ ip"
                }, 
                {
                    "code": "COMPUTER NETWORK ENGINEERING TECHNOLOGY 290", 
                    "course_url": "http://www.chegg.com/courses/1586071/COMPUTER%20NETWORK%20ENGINEERING%20TECHNOLOGY/290", 
                    "name": "Special Topics: Computer Service And Network Technology"
                }
            ], 
            "name": "", 
            "url": "http://www.chegg.com/courses/1586071/COMPUTER%20NETWORK%20ENGINEERING%20TECHNOLOGY"
        }, 
        {
            "abbr": "COMPUTER SCIENCE", 
            "courses": [
                {
                    "code": "COMPUTER SCIENCE 209", 
                    "course_url": "http://www.chegg.com/courses/1586071/COMPUTER%20SCIENCE/209", 
                    "name": "Introduction to Computer Science"
                }, 
                {
                    "code": "COMPUTER SCIENCE 210", 
                    "course_url": "http://www.chegg.com/courses/1586071/COMPUTER%20SCIENCE/210", 
                    "name": "Data Structures And Algorithms I"
                }
            ], 
            "name": "", 
            "url": "http://www.chegg.com/courses/1586071/COMPUTER%20SCIENCE"
        }, 
        {
            "abbr": "CRIMINAL JUSTICE TECHNOLOGY", 
            "courses": [
                {
                    "code": "CRIMINAL JUSTICE TECHNOLOGY 100", 
                    "course_url": "http://www.chegg.com/courses/1586071/CRIMINAL%20JUSTICE%20TECHNOLOGY/100", 
                    "name": "Introduction to Criminal Justice"
                }
            ], 
            "name": "", 
            "url": "http://www.chegg.com/courses/1586071/CRIMINAL%20JUSTICE%20TECHNOLOGY"
        }, 
        {
            "abbr": "CURRICULUM AND INSTRUCTION", 
            "courses": [
                {
                    "code": "CURRICULUM AND INSTRUCTION 230", 
                    "course_url": "http://www.chegg.com/courses/1586071/CURRICULUM%20AND%20INSTRUCTION/230", 
                    "name": "Education Technology"
                }, 
                {
                    "code": "CURRICULUM AND INSTRUCTION 245", 
                    "course_url": "http://www.chegg.com/courses/1586071/CURRICULUM%20AND%20INSTRUCTION/245", 
                    "name": "Understanding Literacy Development And Phonics"
                }, 
                {
                    "code": "CURRICULUM AND INSTRUCTION 286", 
                    "course_url": "http://www.chegg.com/courses/1586071/CURRICULUM%20AND%20INSTRUCTION/286", 
                    "name": "Teaching Multiple Texts Through Genre"
                }
            ], 
            "name": "", 
            "url": "http://www.chegg.com/courses/1586071/CURRICULUM%20AND%20INSTRUCTION"
        }, 
        {
            "abbr": "DEVELOPMENTAL PROGRAMS", 
            "courses": [
                {
                    "code": "DEVELOPMENTAL PROGRAMS 042", 
                    "course_url": "http://www.chegg.com/courses/1586071/DEVELOPMENTAL%20PROGRAMS/042", 
                    "name": "Basic Writing"
                }, 
                {
                    "code": "DEVELOPMENTAL PROGRAMS 050", 
                    "course_url": "http://www.chegg.com/courses/1586071/DEVELOPMENTAL%20PROGRAMS/050", 
                    "name": "Basic Mathematics I"
                }, 
                {
                    "code": "DEVELOPMENTAL PROGRAMS 052", 
                    "course_url": "http://www.chegg.com/courses/1586071/DEVELOPMENTAL%20PROGRAMS/052", 
                    "name": "Basic Mathematics II"
                }, 
                {
                    "code": "DEVELOPMENTAL PROGRAMS 060", 
                    "course_url": "http://www.chegg.com/courses/1586071/DEVELOPMENTAL%20PROGRAMS/060", 
                    "name": "College Reading"
                }, 
                {
                    "code": "DEVELOPMENTAL PROGRAMS 062", 
                    "course_url": "http://www.chegg.com/courses/1586071/DEVELOPMENTAL%20PROGRAMS/062", 
                    "name": "College Reading And Study Skills"
                }, 
                {
                    "code": "DEVELOPMENTAL PROGRAMS 064", 
                    "course_url": "http://www.chegg.com/courses/1586071/DEVELOPMENTAL%20PROGRAMS/064", 
                    "name": "Applied Study Strategies"
                }
            ], 
            "name": "", 
            "url": "http://www.chegg.com/courses/1586071/DEVELOPMENTAL%20PROGRAMS"
        }, 
        {
            "abbr": "DISTINGUISHED STUDENT PROGRAM", 
            "courses": [
                {
                    "code": "DISTINGUISHED STUDENT PROGRAM 150", 
                    "course_url": "http://www.chegg.com/courses/1586071/DISTINGUISHED%20STUDENT%20PROGRAM/150", 
                    "name": "Distinguished Student Colloquium"
                }
            ], 
            "name": "", 
            "url": "http://www.chegg.com/courses/1586071/DISTINGUISHED%20STUDENT%20PROGRAM"
        }, 
        {
            "abbr": "ECONOMICS", 
            "courses": [
                {
                    "code": "ECONOMICS 200", 
                    "course_url": "http://www.chegg.com/courses/1586071/ECONOMICS/200", 
                    "name": "Principles of Microeconomics"
                }, 
                {
                    "code": "ECONOMICS 201", 
                    "course_url": "http://www.chegg.com/courses/1586071/ECONOMICS/201", 
                    "name": "Principles of Macroeconomics"
                }, 
                {
                    "code": "ECONOMICS 244", 
                    "course_url": "http://www.chegg.com/courses/1586071/ECONOMICS/244", 
                    "name": "Introduction to Economic Analysis"
                }
            ], 
            "name": "Economics", 
            "url": "http://www.chegg.com/courses/1586071/ECONOMICS"
        }, 
        {
            "abbr": "EDUCATIONAL FOUNDATIONS AND LEADERSHIP", 
            "courses": [
                {
                    "code": "EDUCATIONAL FOUNDATIONS AND LEADERSHIP 200", 
                    "course_url": "http://www.chegg.com/courses/1586071/EDUCATIONAL%20FOUNDATIONS%20AND%20LEADERSHIP/200", 
                    "name": "Introduction to Education"
                }, 
                {
                    "code": "EDUCATIONAL FOUNDATIONS AND LEADERSHIP 220", 
                    "course_url": "http://www.chegg.com/courses/1586071/EDUCATIONAL%20FOUNDATIONS%20AND%20LEADERSHIP/220", 
                    "name": "Educational Psychology"
                }
            ], 
            "name": "", 
            "url": "http://www.chegg.com/courses/1586071/EDUCATIONAL%20FOUNDATIONS%20AND%20LEADERSHIP"
        }, 
        {
            "abbr": "ELECTRICAL ENGINEERING", 
            "courses": [
                {
                    "code": "ELECTRICAL ENGINEERING 230", 
                    "course_url": "http://www.chegg.com/courses/1586071/ELECTRICAL%20ENGINEERING/230", 
                    "name": "Circuits I Laboratory"
                }, 
                {
                    "code": "ELECTRICAL ENGINEERING 231", 
                    "course_url": "http://www.chegg.com/courses/1586071/ELECTRICAL%20ENGINEERING/231", 
                    "name": "Circuits I"
                }
            ], 
            "name": "", 
            "url": "http://www.chegg.com/courses/1586071/ELECTRICAL%20ENGINEERING"
        }, 
        {
            "abbr": "ELEMENTARY EDUCATION", 
            "courses": [
                {
                    "code": "ELEMENTARY EDUCATION 215", 
                    "course_url": "http://www.chegg.com/courses/1586071/ELEMENTARY%20EDUCATION/215", 
                    "name": "The Child, The Family"
                }
            ], 
            "name": "", 
            "url": "http://www.chegg.com/courses/1586071/ELEMENTARY%20EDUCATION"
        }, 
        {
            "abbr": "ENGLISH", 
            "courses": [
                {
                    "code": "ENGLISH 111", 
                    "course_url": "http://www.chegg.com/courses/1586071/ENGLISH/111", 
                    "name": "English Composition I"
                }, 
                {
                    "code": "ENGLISH 112", 
                    "course_url": "http://www.chegg.com/courses/1586071/ENGLISH/112", 
                    "name": "English Composition II"
                }, 
                {
                    "code": "ENGLISH 222", 
                    "course_url": "http://www.chegg.com/courses/1586071/ENGLISH/222", 
                    "name": "Technical Report Writing"
                }, 
                {
                    "code": "ENGLISH 250", 
                    "course_url": "http://www.chegg.com/courses/1586071/ENGLISH/250", 
                    "name": "Classic And Contemporary Literature"
                }, 
                {
                    "code": "ENGLISH 252", 
                    "course_url": "http://www.chegg.com/courses/1586071/ENGLISH/252", 
                    "name": "Shakespeare And His World"
                }, 
                {
                    "code": "ENGLISH 275", 
                    "course_url": "http://www.chegg.com/courses/1586071/ENGLISH/275", 
                    "name": "Specialized Writing"
                }, 
                {
                    "code": "ENGLISH 277", 
                    "course_url": "http://www.chegg.com/courses/1586071/ENGLISH/277", 
                    "name": "Introduction to Poetry Writing"
                }, 
                {
                    "code": "ENGLISH 278", 
                    "course_url": "http://www.chegg.com/courses/1586071/ENGLISH/278", 
                    "name": "Introduction to Fiction Writing"
                }, 
                {
                    "code": "ENGLISH 280", 
                    "course_url": "http://www.chegg.com/courses/1586071/ENGLISH/280", 
                    "name": "Poetry Appreciation"
                }, 
                {
                    "code": "ENGLISH 281", 
                    "course_url": "http://www.chegg.com/courses/1586071/ENGLISH/281", 
                    "name": "Fiction Appreciation"
                }, 
                {
                    "code": "ENGLISH 282", 
                    "course_url": "http://www.chegg.com/courses/1586071/ENGLISH/282", 
                    "name": "Drama Appreciation"
                }, 
                {
                    "code": "ENGLISH 283", 
                    "course_url": "http://www.chegg.com/courses/1586071/ENGLISH/283", 
                    "name": "Film Appreciation"
                }, 
                {
                    "code": "ENGLISH 290", 
                    "course_url": "http://www.chegg.com/courses/1586071/ENGLISH/290", 
                    "name": "Special Topics: Associate Studies"
                }
            ], 
            "name": "English", 
            "url": "http://www.chegg.com/courses/1586071/ENGLISH"
        }, 
        {
            "abbr": "ENTREPRENEURSHIP", 
            "courses": [
                {
                    "code": "ENTREPRENEURSHIP 201", 
                    "course_url": "http://www.chegg.com/courses/1586071/ENTREPRENEURSHIP/201", 
                    "name": "Introduction to Entrepreneurship"
                }
            ], 
            "name": "", 
            "url": "http://www.chegg.com/courses/1586071/ENTREPRENEURSHIP"
        }, 
        {
            "abbr": "ENVIRONMENTAL HEALTH AND SAFETY TECHNOLOGY", 
            "courses": [
                {
                    "code": "ENVIRONMENTAL HEALTH AND SAFETY TECHNOLOGY 200", 
                    "course_url": "http://www.chegg.com/courses/1586071/ENVIRONMENTAL%20HEALTH%20AND%20SAFETY%20TECHNOLOGY/200", 
                    "name": "Internet: Physics For Environmental Technicians"
                }, 
                {
                    "code": "ENVIRONMENTAL HEALTH AND SAFETY TECHNOLOGY 210", 
                    "course_url": "http://www.chegg.com/courses/1586071/ENVIRONMENTAL%20HEALTH%20AND%20SAFETY%20TECHNOLOGY/210", 
                    "name": "Occupational Safety And Risk"
                }, 
                {
                    "code": "ENVIRONMENTAL HEALTH AND SAFETY TECHNOLOGY 220", 
                    "course_url": "http://www.chegg.com/courses/1586071/ENVIRONMENTAL%20HEALTH%20AND%20SAFETY%20TECHNOLOGY/220", 
                    "name": "Environmental Law And Regulations"
                }, 
                {
                    "code": "ENVIRONMENTAL HEALTH AND SAFETY TECHNOLOGY 221", 
                    "course_url": "http://www.chegg.com/courses/1586071/ENVIRONMENTAL%20HEALTH%20AND%20SAFETY%20TECHNOLOGY/221", 
                    "name": "Environmental Law And Regulations II"
                }, 
                {
                    "code": "ENVIRONMENTAL HEALTH AND SAFETY TECHNOLOGY 230", 
                    "course_url": "http://www.chegg.com/courses/1586071/ENVIRONMENTAL%20HEALTH%20AND%20SAFETY%20TECHNOLOGY/230", 
                    "name": "Water And Atmospheric Pollution"
                }, 
                {
                    "code": "ENVIRONMENTAL HEALTH AND SAFETY TECHNOLOGY 232", 
                    "course_url": "http://www.chegg.com/courses/1586071/ENVIRONMENTAL%20HEALTH%20AND%20SAFETY%20TECHNOLOGY/232", 
                    "name": "Environmental Sampling Laboratory"
                }, 
                {
                    "code": "ENVIRONMENTAL HEALTH AND SAFETY TECHNOLOGY 250", 
                    "course_url": "http://www.chegg.com/courses/1586071/ENVIRONMENTAL%20HEALTH%20AND%20SAFETY%20TECHNOLOGY/250", 
                    "name": "Internship: Environmental Health And Safety"
                }, 
                {
                    "code": "ENVIRONMENTAL HEALTH AND SAFETY TECHNOLOGY 290", 
                    "course_url": "http://www.chegg.com/courses/1586071/ENVIRONMENTAL%20HEALTH%20AND%20SAFETY%20TECHNOLOGY/290", 
                    "name": "Special Topics in Environmental Health And Safety Technology"
                }
            ], 
            "name": "", 
            "url": "http://www.chegg.com/courses/1586071/ENVIRONMENTAL%20HEALTH%20AND%20SAFETY%20TECHNOLOGY"
        }, 
        {
            "abbr": "FAMILY AND CONSUMER SCIENCES", 
            "courses": [
                {
                    "code": "FAMILY AND CONSUMER SCIENCES 133", 
                    "course_url": "http://www.chegg.com/courses/1586071/FAMILY%20AND%20CONSUMER%20SCIENCES/133", 
                    "name": "Nutrition Fundamentals"
                }, 
                {
                    "code": "FAMILY AND CONSUMER SCIENCES 265", 
                    "course_url": "http://www.chegg.com/courses/1586071/FAMILY%20AND%20CONSUMER%20SCIENCES/265", 
                    "name": "Child Development"
                }, 
                {
                    "code": "FAMILY AND CONSUMER SCIENCES 270", 
                    "course_url": "http://www.chegg.com/courses/1586071/FAMILY%20AND%20CONSUMER%20SCIENCES/270", 
                    "name": "Theory And Guidance of Play"
                }, 
                {
                    "code": "FAMILY AND CONSUMER SCIENCES 280", 
                    "course_url": "http://www.chegg.com/courses/1586071/FAMILY%20AND%20CONSUMER%20SCIENCES/280", 
                    "name": "Early Childhood Curriculum Methods"
                }
            ], 
            "name": "", 
            "url": "http://www.chegg.com/courses/1586071/FAMILY%20AND%20CONSUMER%20SCIENCES"
        }, 
        {
            "abbr": "FINANCE", 
            "courses": [
                {
                    "code": "FINANCE 220", 
                    "course_url": "http://www.chegg.com/courses/1586071/FINANCE/220", 
                    "name": "The Legal And Social Environment of Business"
                }
            ], 
            "name": "Finance", 
            "url": "http://www.chegg.com/courses/1586071/FINANCE"
        }, 
        {
            "abbr": "GENERAL BUSINESS", 
            "courses": [
                {
                    "code": "GENERAL BUSINESS 101", 
                    "course_url": "http://www.chegg.com/courses/1586071/GENERAL%20BUSINESS/101", 
                    "name": "Global Business Concepts & Practices"
                }
            ], 
            "name": "", 
            "url": "http://www.chegg.com/courses/1586071/GENERAL%20BUSINESS"
        }, 
        {
            "abbr": "GENERAL EDUCATION", 
            "courses": [
                {
                    "code": "GENERAL EDUCATION 101", 
                    "course_url": "http://www.chegg.com/courses/1586071/GENERAL%20EDUCATION/101", 
                    "name": "Student Success Seminar"
                }
            ], 
            "name": "", 
            "url": "http://www.chegg.com/courses/1586071/GENERAL%20EDUCATION"
        }, 
        {
            "abbr": "GENERAL ENGINEERING", 
            "courses": [
                {
                    "code": "GENERAL ENGINEERING 101", 
                    "course_url": "http://www.chegg.com/courses/1586071/GENERAL%20ENGINEERING/101", 
                    "name": "Tools For Engineering"
                }
            ], 
            "name": "", 
            "url": "http://www.chegg.com/courses/1586071/GENERAL%20ENGINEERING"
        }, 
        {
            "abbr": "GENERAL TECHNOLOGY", 
            "courses": [
                {
                    "code": "GENERAL TECHNOLOGY 105", 
                    "course_url": "http://www.chegg.com/courses/1586071/GENERAL%20TECHNOLOGY/105", 
                    "name": "Basic Chemistry"
                }, 
                {
                    "code": "GENERAL TECHNOLOGY 161", 
                    "course_url": "http://www.chegg.com/courses/1586071/GENERAL%20TECHNOLOGY/161", 
                    "name": "Technical Physics: Mechanics I"
                }, 
                {
                    "code": "GENERAL TECHNOLOGY 162", 
                    "course_url": "http://www.chegg.com/courses/1586071/GENERAL%20TECHNOLOGY/162", 
                    "name": "Technical Physics: Mechanics II"
                }, 
                {
                    "code": "GENERAL TECHNOLOGY 163", 
                    "course_url": "http://www.chegg.com/courses/1586071/GENERAL%20TECHNOLOGY/163", 
                    "name": "Technical Physics: Electricity And Magnetism"
                }
            ], 
            "name": "", 
            "url": "http://www.chegg.com/courses/1586071/GENERAL%20TECHNOLOGY"
        }, 
        {
            "abbr": "GEOGRAPHY AND PLANNING", 
            "courses": [
                {
                    "code": "GEOGRAPHY AND PLANNING 100", 
                    "course_url": "http://www.chegg.com/courses/1586071/GEOGRAPHY%20AND%20PLANNING/100", 
                    "name": "Introduction to Geography"
                }, 
                {
                    "code": "GEOGRAPHY AND PLANNING 375", 
                    "course_url": "http://www.chegg.com/courses/1586071/GEOGRAPHY%20AND%20PLANNING/375", 
                    "name": "Geography of Cultural Diversity"
                }
            ], 
            "name": "", 
            "url": "http://www.chegg.com/courses/1586071/GEOGRAPHY%20AND%20PLANNING"
        }, 
        {
            "abbr": "GEOLOGY", 
            "courses": [
                {
                    "code": "GEOLOGY 100", 
                    "course_url": "http://www.chegg.com/courses/1586071/GEOLOGY/100", 
                    "name": "Earth Science"
                }, 
                {
                    "code": "GEOLOGY 101", 
                    "course_url": "http://www.chegg.com/courses/1586071/GEOLOGY/101", 
                    "name": "Introductory Physical Geology"
                }, 
                {
                    "code": "GEOLOGY 102", 
                    "course_url": "http://www.chegg.com/courses/1586071/GEOLOGY/102", 
                    "name": "Introductory Historical Geology"
                }, 
                {
                    "code": "GEOLOGY 103", 
                    "course_url": "http://www.chegg.com/courses/1586071/GEOLOGY/103", 
                    "name": "Natural Science: Geology"
                }, 
                {
                    "code": "GEOLOGY 121", 
                    "course_url": "http://www.chegg.com/courses/1586071/GEOLOGY/121", 
                    "name": "Dinosaurs"
                }, 
                {
                    "code": "GEOLOGY 121-140", 
                    "course_url": "http://www.chegg.com/courses/1586071/GEOLOGY/121-140", 
                    "name": "Concepts of Geology"
                }, 
                {
                    "code": "GEOLOGY 122", 
                    "course_url": "http://www.chegg.com/courses/1586071/GEOLOGY/122", 
                    "name": "Mass Extinctions And Geology"
                }, 
                {
                    "code": "GEOLOGY 123", 
                    "course_url": "http://www.chegg.com/courses/1586071/GEOLOGY/123", 
                    "name": "Interpreting Earth's Geological History"
                }, 
                {
                    "code": "GEOLOGY 124", 
                    "course_url": "http://www.chegg.com/courses/1586071/GEOLOGY/124", 
                    "name": "Plate Tectonics: The New Geology"
                }, 
                {
                    "code": "GEOLOGY 125", 
                    "course_url": "http://www.chegg.com/courses/1586071/GEOLOGY/125", 
                    "name": "Earthquakes: Why, Where And When?"
                }, 
                {
                    "code": "GEOLOGY 126", 
                    "course_url": "http://www.chegg.com/courses/1586071/GEOLOGY/126", 
                    "name": "Natural Disasters And Geology"
                }, 
                {
                    "code": "GEOLOGY 127", 
                    "course_url": "http://www.chegg.com/courses/1586071/GEOLOGY/127", 
                    "name": "The Ice Age And Ohio"
                }, 
                {
                    "code": "GEOLOGY 128", 
                    "course_url": "http://www.chegg.com/courses/1586071/GEOLOGY/128", 
                    "name": "Geology of Ohio"
                }, 
                {
                    "code": "GEOLOGY 129", 
                    "course_url": "http://www.chegg.com/courses/1586071/GEOLOGY/129", 
                    "name": "Medical Geology"
                }, 
                {
                    "code": "GEOLOGY 130", 
                    "course_url": "http://www.chegg.com/courses/1586071/GEOLOGY/130", 
                    "name": "Geologic Record of Climate Change"
                }, 
                {
                    "code": "GEOLOGY 131", 
                    "course_url": "http://www.chegg.com/courses/1586071/GEOLOGY/131", 
                    "name": "Geology And Society"
                }, 
                {
                    "code": "GEOLOGY 132", 
                    "course_url": "http://www.chegg.com/courses/1586071/GEOLOGY/132", 
                    "name": "Gemstones And Precious Metals"
                }, 
                {
                    "code": "GEOLOGY 133", 
                    "course_url": "http://www.chegg.com/courses/1586071/GEOLOGY/133", 
                    "name": "Caves"
                }, 
                {
                    "code": "GEOLOGY 134", 
                    "course_url": "http://www.chegg.com/courses/1586071/GEOLOGY/134", 
                    "name": "Hazardo us And Nuclear Waste Disposal"
                }, 
                {
                    "code": "GEOLOGY 135", 
                    "course_url": "http://www.chegg.com/courses/1586071/GEOLOGY/135", 
                    "name": "Geology of Energy Resources"
                }, 
                {
                    "code": "GEOLOGY 137", 
                    "course_url": "http://www.chegg.com/courses/1586071/GEOLOGY/137", 
                    "name": "Earth's Atmosphere And Weather"
                }, 
                {
                    "code": "GEOLOGY 138", 
                    "course_url": "http://www.chegg.com/courses/1586071/GEOLOGY/138", 
                    "name": "Planetary Geology"
                }, 
                {
                    "code": "GEOLOGY 140", 
                    "course_url": "http://www.chegg.com/courses/1586071/GEOLOGY/140", 
                    "name": "Rocky Mountain National Parks"
                }, 
                {
                    "code": "GEOLOGY 171", 
                    "course_url": "http://www.chegg.com/courses/1586071/GEOLOGY/171", 
                    "name": "Introduction to The Oceans"
                }, 
                {
                    "code": "GEOLOGY 200", 
                    "course_url": "http://www.chegg.com/courses/1586071/GEOLOGY/200", 
                    "name": "Environmental Geology"
                }, 
                {
                    "code": "GEOLOGY 201", 
                    "course_url": "http://www.chegg.com/courses/1586071/GEOLOGY/201", 
                    "name": "Exercises in Environmental Geology I"
                }, 
                {
                    "code": "GEOLOGY 203", 
                    "course_url": "http://www.chegg.com/courses/1586071/GEOLOGY/203", 
                    "name": "Exercises in Environmental Geology II"
                }
            ], 
            "name": "Geology", 
            "url": "http://www.chegg.com/courses/1586071/GEOLOGY"
        }, 
        {
            "abbr": "GERMAN", 
            "courses": [
                {
                    "code": "GERMAN 101 ,2", 
                    "course_url": "http://www.chegg.com/courses/1586071/GERMAN/101%20%2C2", 
                    "name": "Beginning German I, II"
                }, 
                {
                    "code": "GERMAN 201 ,2", 
                    "course_url": "http://www.chegg.com/courses/1586071/GERMAN/201%20%2C2", 
                    "name": "Intermediate German I, II"
                }
            ], 
            "name": "Germanics", 
            "url": "http://www.chegg.com/courses/1586071/GERMAN"
        }, 
        {
            "abbr": "HEALTH CARE OFFICE MANAGEMENT", 
            "courses": [
                {
                    "code": "HEALTH CARE OFFICE MANAGEMENT 240", 
                    "course_url": "http://www.chegg.com/courses/1586071/HEALTH%20CARE%20OFFICE%20MANAGEMENT/240", 
                    "name": "Medical Coding I- Diagnostic"
                }, 
                {
                    "code": "HEALTH CARE OFFICE MANAGEMENT 241", 
                    "course_url": "http://www.chegg.com/courses/1586071/HEALTH%20CARE%20OFFICE%20MANAGEMENT/241", 
                    "name": "Health Information Management"
                }, 
                {
                    "code": "HEALTH CARE OFFICE MANAGEMENT 242", 
                    "course_url": "http://www.chegg.com/courses/1586071/HEALTH%20CARE%20OFFICE%20MANAGEMENT/242", 
                    "name": "Medical Office Administration"
                }, 
                {
                    "code": "HEALTH CARE OFFICE MANAGEMENT 243", 
                    "course_url": "http://www.chegg.com/courses/1586071/HEALTH%20CARE%20OFFICE%20MANAGEMENT/243", 
                    "name": "Medical Coding II- Procedural"
                }, 
                {
                    "code": "HEALTH CARE OFFICE MANAGEMENT 244", 
                    "course_url": "http://www.chegg.com/courses/1586071/HEALTH%20CARE%20OFFICE%20MANAGEMENT/244", 
                    "name": "Medical Insurance Billing"
                }, 
                {
                    "code": "HEALTH CARE OFFICE MANAGEMENT 255", 
                    "course_url": "http://www.chegg.com/courses/1586071/HEALTH%20CARE%20OFFICE%20MANAGEMENT/255", 
                    "name": "Health Care Office Management And Medicolegal Issues"
                }, 
                {
                    "code": "HEALTH CARE OFFICE MANAGEMENT 257", 
                    "course_url": "http://www.chegg.com/courses/1586071/HEALTH%20CARE%20OFFICE%20MANAGEMENT/257", 
                    "name": "Health Care Office Finance"
                }, 
                {
                    "code": "HEALTH CARE OFFICE MANAGEMENT 260", 
                    "course_url": "http://www.chegg.com/courses/1586071/HEALTH%20CARE%20OFFICE%20MANAGEMENT/260", 
                    "name": "Health Care Office Management Internship"
                }, 
                {
                    "code": "HEALTH CARE OFFICE MANAGEMENT 284", 
                    "course_url": "http://www.chegg.com/courses/1586071/HEALTH%20CARE%20OFFICE%20MANAGEMENT/284", 
                    "name": "Medical Office Techniques"
                }, 
                {
                    "code": "HEALTH CARE OFFICE MANAGEMENT 290", 
                    "course_url": "http://www.chegg.com/courses/1586071/HEALTH%20CARE%20OFFICE%20MANAGEMENT/290", 
                    "name": "Special Topics in Health Care Office Management"
                }
            ], 
            "name": "", 
            "url": "http://www.chegg.com/courses/1586071/HEALTH%20CARE%20OFFICE%20MANAGEMENT"
        }, 
        {
            "abbr": "HEALTH EDUCATION", 
            "courses": [
                {
                    "code": "HEALTH EDUCATION 101", 
                    "course_url": "http://www.chegg.com/courses/1586071/HEALTH%20EDUCATION/101", 
                    "name": "Personal Health"
                }
            ], 
            "name": "", 
            "url": "http://www.chegg.com/courses/1586071/HEALTH%20EDUCATION"
        }, 
        {
            "abbr": "HISTORY", 
            "courses": [
                {
                    "code": "HISTORY 210", 
                    "course_url": "http://www.chegg.com/courses/1586071/HISTORY/210", 
                    "name": "Humanities in The Western Tradition I: Antiquity to The Renaissance"
                }, 
                {
                    "code": "HISTORY 211", 
                    "course_url": "http://www.chegg.com/courses/1586071/HISTORY/211", 
                    "name": "Humanities in The Western Tradition II: Reformation to The Present"
                }, 
                {
                    "code": "HISTORY 250", 
                    "course_url": "http://www.chegg.com/courses/1586071/HISTORY/250", 
                    "name": "United States History to 1877"
                }, 
                {
                    "code": "HISTORY 251", 
                    "course_url": "http://www.chegg.com/courses/1586071/HISTORY/251", 
                    "name": "United States History Since 1877"
                }, 
                {
                    "code": "HISTORY 385", 
                    "course_url": "http://www.chegg.com/courses/1586071/HISTORY/385", 
                    "name": "World Civilizations: China"
                }, 
                {
                    "code": "HISTORY 386", 
                    "course_url": "http://www.chegg.com/courses/1586071/HISTORY/386", 
                    "name": "World Civilizations: Japan"
                }, 
                {
                    "code": "HISTORY 387", 
                    "course_url": "http://www.chegg.com/courses/1586071/HISTORY/387", 
                    "name": "World Civilizations: Southeast Asia"
                }, 
                {
                    "code": "HISTORY 388", 
                    "course_url": "http://www.chegg.com/courses/1586071/HISTORY/388", 
                    "name": "World Civilizations: India"
                }, 
                {
                    "code": "HISTORY 389", 
                    "course_url": "http://www.chegg.com/courses/1586071/HISTORY/389", 
                    "name": "World Civilizations: Middle East"
                }, 
                {
                    "code": "HISTORY 390", 
                    "course_url": "http://www.chegg.com/courses/1586071/HISTORY/390", 
                    "name": "World Civilizations: Africa"
                }, 
                {
                    "code": "HISTORY 391", 
                    "course_url": "http://www.chegg.com/courses/1586071/HISTORY/391", 
                    "name": "World Civilizations: Latin America"
                }
            ], 
            "name": "History", 
            "url": "http://www.chegg.com/courses/1586071/HISTORY"
        }, 
        {
            "abbr": "INDIVIDUAL STUDY", 
            "courses": [
                {
                    "code": "INDIVIDUAL STUDY 190", 
                    "course_url": "http://www.chegg.com/courses/1586071/INDIVIDUAL%20STUDY/190", 
                    "name": "Individualized Study"
                }
            ], 
            "name": "", 
            "url": "http://www.chegg.com/courses/1586071/INDIVIDUAL%20STUDY"
        }, 
        {
            "abbr": "MANAGEMENT", 
            "courses": [
                {
                    "code": "MANAGEMENT 221", 
                    "course_url": "http://www.chegg.com/courses/1586071/MANAGEMENT/221", 
                    "name": "Quantitative Business Analysis I"
                }, 
                {
                    "code": "MANAGEMENT 222", 
                    "course_url": "http://www.chegg.com/courses/1586071/MANAGEMENT/222", 
                    "name": "Quantitative Business Analysis II"
                }
            ], 
            "name": "", 
            "url": "http://www.chegg.com/courses/1586071/MANAGEMENT"
        }, 
        {
            "abbr": "MANUFACTURING ENGINEERING TECHNOLOGY", 
            "courses": [
                {
                    "code": "MANUFACTURING ENGINEERING TECHNOLOGY 232", 
                    "course_url": "http://www.chegg.com/courses/1586071/MANUFACTURING%20ENGINEERING%20TECHNOLOGY/232", 
                    "name": "Labor Management Relations"
                }
            ], 
            "name": "", 
            "url": "http://www.chegg.com/courses/1586071/MANUFACTURING%20ENGINEERING%20TECHNOLOGY"
        }, 
        {
            "abbr": "MARKETING AND SALES TECHNOLOGY", 
            "courses": [
                {
                    "code": "MARKETING AND SALES TECHNOLOGY 101", 
                    "course_url": "http://www.chegg.com/courses/1586071/MARKETING%20AND%20SALES%20TECHNOLOGY/101", 
                    "name": "Essentials of Marketing Technology"
                }
            ], 
            "name": "", 
            "url": "http://www.chegg.com/courses/1586071/MARKETING%20AND%20SALES%20TECHNOLOGY"
        }, 
        {
            "abbr": "MATHEMATICS", 
            "courses": [
                {
                    "code": "MATHEMATICS 100", 
                    "course_url": "http://www.chegg.com/courses/1586071/MATHEMATICS/100", 
                    "name": "Intermediate Algebra"
                }, 
                {
                    "code": "MATHEMATICS 130", 
                    "course_url": "http://www.chegg.com/courses/1586071/MATHEMATICS/130", 
                    "name": "Mathematics For Allied Health"
                }, 
                {
                    "code": "MATHEMATICS 135", 
                    "course_url": "http://www.chegg.com/courses/1586071/MATHEMATICS/135", 
                    "name": "Excursion in Mathematics"
                }, 
                {
                    "code": "MATHEMATICS 140", 
                    "course_url": "http://www.chegg.com/courses/1586071/MATHEMATICS/140", 
                    "name": "Mathematics For Elementary School Teachers I"
                }, 
                {
                    "code": "MATHEMATICS 145", 
                    "course_url": "http://www.chegg.com/courses/1586071/MATHEMATICS/145", 
                    "name": "College Algebra"
                }, 
                {
                    "code": "MATHEMATICS 149", 
                    "course_url": "http://www.chegg.com/courses/1586071/MATHEMATICS/149", 
                    "name": "Precalculus Mathematics"
                }, 
                {
                    "code": "MATHEMATICS 151", 
                    "course_url": "http://www.chegg.com/courses/1586071/MATHEMATICS/151", 
                    "name": "Technical Mathematics I"
                }, 
                {
                    "code": "MATHEMATICS 152", 
                    "course_url": "http://www.chegg.com/courses/1586071/MATHEMATICS/152", 
                    "name": "Technical Mathematics II"
                }, 
                {
                    "code": "MATHEMATICS 153", 
                    "course_url": "http://www.chegg.com/courses/1586071/MATHEMATICS/153", 
                    "name": "Technical Mathematics III"
                }, 
                {
                    "code": "MATHEMATICS 161", 
                    "course_url": "http://www.chegg.com/courses/1586071/MATHEMATICS/161", 
                    "name": "Mathematics For Modern Technology"
                }, 
                {
                    "code": "MATHEMATICS 210", 
                    "course_url": "http://www.chegg.com/courses/1586071/MATHEMATICS/210", 
                    "name": "Calculus With Business Applications"
                }, 
                {
                    "code": "MATHEMATICS 215", 
                    "course_url": "http://www.chegg.com/courses/1586071/MATHEMATICS/215", 
                    "name": "Concepts of Calculus"
                }, 
                {
                    "code": "MATHEMATICS 221", 
                    "course_url": "http://www.chegg.com/courses/1586071/MATHEMATICS/221", 
                    "name": "Analytic Geometry- Calculus I"
                }, 
                {
                    "code": "MATHEMATICS 222", 
                    "course_url": "http://www.chegg.com/courses/1586071/MATHEMATICS/222", 
                    "name": "Analytic Geometry- Calculus II"
                }, 
                {
                    "code": "MATHEMATICS 223", 
                    "course_url": "http://www.chegg.com/courses/1586071/MATHEMATICS/223", 
                    "name": "Analytic Geometry- Calculus III"
                }, 
                {
                    "code": "MATHEMATICS 260", 
                    "course_url": "http://www.chegg.com/courses/1586071/MATHEMATICS/260", 
                    "name": "Mathematics For Elementary School Teachers II"
                }, 
                {
                    "code": "MATHEMATICS 289", 
                    "course_url": "http://www.chegg.com/courses/1586071/MATHEMATICS/289", 
                    "name": "Selected Topics in Mathematics"
                }, 
                {
                    "code": "MATHEMATICS 335", 
                    "course_url": "http://www.chegg.com/courses/1586071/MATHEMATICS/335", 
                    "name": "Introduction to Ordinary Differential Equations"
                }
            ], 
            "name": "Pre-Credit", 
            "url": "http://www.chegg.com/courses/1586071/MATHEMATICS"
        }, 
        {
            "abbr": "MECHANICAL ENGINEERING", 
            "courses": [
                {
                    "code": "MECHANICAL ENGINEERING 165", 
                    "course_url": "http://www.chegg.com/courses/1586071/MECHANICAL%20ENGINEERING/165", 
                    "name": "Tools For Mechanical Engineering"
                }, 
                {
                    "code": "MECHANICAL ENGINEERING 203", 
                    "course_url": "http://www.chegg.com/courses/1586071/MECHANICAL%20ENGINEERING/203", 
                    "name": "Dynamics"
                }
            ], 
            "name": "", 
            "url": "http://www.chegg.com/courses/1586071/MECHANICAL%20ENGINEERING"
        }, 
        {
            "abbr": "MEDICAL ASSISTING", 
            "courses": [
                {
                    "code": "MEDICAL ASSISTING 120", 
                    "course_url": "http://www.chegg.com/courses/1586071/MEDICAL%20ASSISTING/120", 
                    "name": "Medical Terminology"
                }, 
                {
                    "code": "MEDICAL ASSISTING 121", 
                    "course_url": "http://www.chegg.com/courses/1586071/MEDICAL%20ASSISTING/121", 
                    "name": "Study of Disease Processes"
                }, 
                {
                    "code": "MEDICAL ASSISTING 230", 
                    "course_url": "http://www.chegg.com/courses/1586071/MEDICAL%20ASSISTING/230", 
                    "name": "Basic Pharmacology"
                }
            ], 
            "name": "", 
            "url": "http://www.chegg.com/courses/1586071/MEDICAL%20ASSISTING"
        }, 
        {
            "abbr": "MUSIC", 
            "courses": [
                {
                    "code": "MUSIC 201", 
                    "course_url": "http://www.chegg.com/courses/1586071/MUSIC/201", 
                    "name": "Exploring Music: Bach to Rock"
                }
            ], 
            "name": "Music", 
            "url": "http://www.chegg.com/courses/1586071/MUSIC"
        }, 
        {
            "abbr": "NURSING", 
            "courses": [
                {
                    "code": "NURSING 100", 
                    "course_url": "http://www.chegg.com/courses/1586071/NURSING/100", 
                    "name": "Introduction to Nursing"
                }
            ], 
            "name": "Nursing", 
            "url": "http://www.chegg.com/courses/1586071/NURSING"
        }, 
        {
            "abbr": "OFFICE TECHNOLOGY", 
            "courses": [
                {
                    "code": "OFFICE TECHNOLOGY 119", 
                    "course_url": "http://www.chegg.com/courses/1586071/OFFICE%20TECHNOLOGY/119", 
                    "name": "Business English"
                }, 
                {
                    "code": "OFFICE TECHNOLOGY 121", 
                    "course_url": "http://www.chegg.com/courses/1586071/OFFICE%20TECHNOLOGY/121", 
                    "name": "Introduction to Office Procedures"
                }, 
                {
                    "code": "OFFICE TECHNOLOGY 123", 
                    "course_url": "http://www.chegg.com/courses/1586071/OFFICE%20TECHNOLOGY/123", 
                    "name": "Microsoft Outlook"
                }, 
                {
                    "code": "OFFICE TECHNOLOGY 136", 
                    "course_url": "http://www.chegg.com/courses/1586071/OFFICE%20TECHNOLOGY/136", 
                    "name": "Speech Recognition Technology"
                }, 
                {
                    "code": "OFFICE TECHNOLOGY 138", 
                    "course_url": "http://www.chegg.com/courses/1586071/OFFICE%20TECHNOLOGY/138", 
                    "name": "Project Management"
                }, 
                {
                    "code": "OFFICE TECHNOLOGY 143", 
                    "course_url": "http://www.chegg.com/courses/1586071/OFFICE%20TECHNOLOGY/143", 
                    "name": "Microsoft Word: Beginning"
                }, 
                {
                    "code": "OFFICE TECHNOLOGY 144", 
                    "course_url": "http://www.chegg.com/courses/1586071/OFFICE%20TECHNOLOGY/144", 
                    "name": "Microsoft Word: Advanced"
                }, 
                {
                    "code": "OFFICE TECHNOLOGY 241", 
                    "course_url": "http://www.chegg.com/courses/1586071/OFFICE%20TECHNOLOGY/241", 
                    "name": "Information Management"
                }, 
                {
                    "code": "OFFICE TECHNOLOGY 243", 
                    "course_url": "http://www.chegg.com/courses/1586071/OFFICE%20TECHNOLOGY/243", 
                    "name": "Internship"
                }, 
                {
                    "code": "OFFICE TECHNOLOGY 253", 
                    "course_url": "http://www.chegg.com/courses/1586071/OFFICE%20TECHNOLOGY/253", 
                    "name": "Advanced Word Processing"
                }, 
                {
                    "code": "OFFICE TECHNOLOGY 263", 
                    "course_url": "http://www.chegg.com/courses/1586071/OFFICE%20TECHNOLOGY/263", 
                    "name": "Professional Communication And Presentations"
                }, 
                {
                    "code": "OFFICE TECHNOLOGY 271", 
                    "course_url": "http://www.chegg.com/courses/1586071/OFFICE%20TECHNOLOGY/271", 
                    "name": "Desktop Publishing"
                }, 
                {
                    "code": "OFFICE TECHNOLOGY 273", 
                    "course_url": "http://www.chegg.com/courses/1586071/OFFICE%20TECHNOLOGY/273", 
                    "name": "Microsoft Powerpoint"
                }, 
                {
                    "code": "OFFICE TECHNOLOGY 279", 
                    "course_url": "http://www.chegg.com/courses/1586071/OFFICE%20TECHNOLOGY/279", 
                    "name": "Legal Office Procedures"
                }, 
                {
                    "code": "OFFICE TECHNOLOGY 281", 
                    "course_url": "http://www.chegg.com/courses/1586071/OFFICE%20TECHNOLOGY/281", 
                    "name": "Editing/ Proofreading/ Transcription"
                }, 
                {
                    "code": "OFFICE TECHNOLOGY 282", 
                    "course_url": "http://www.chegg.com/courses/1586071/OFFICE%20TECHNOLOGY/282", 
                    "name": "Medical Machine Transcription"
                }, 
                {
                    "code": "OFFICE TECHNOLOGY 289", 
                    "course_url": "http://www.chegg.com/courses/1586071/OFFICE%20TECHNOLOGY/289", 
                    "name": "Career Development For Business Professionals"
                }, 
                {
                    "code": "OFFICE TECHNOLOGY 290", 
                    "course_url": "http://www.chegg.com/courses/1586071/OFFICE%20TECHNOLOGY/290", 
                    "name": "Special Topics: Office Administration"
                }
            ], 
            "name": "", 
            "url": "http://www.chegg.com/courses/1586071/OFFICE%20TECHNOLOGY"
        }, 
        {
            "abbr": "PARAPROFESSIONAL EDUCATION", 
            "courses": [
                {
                    "code": "PARAPROFESSIONAL EDUCATION 290", 
                    "course_url": "http://www.chegg.com/courses/1586071/PARAPROFESSIONAL%20EDUCATION/290", 
                    "name": "Spe Cial Topics: Paraprofessional Education"
                }
            ], 
            "name": "", 
            "url": "http://www.chegg.com/courses/1586071/PARAPROFESSIONAL%20EDUCATION"
        }, 
        {
            "abbr": "PHILOSOPHY", 
            "courses": [
                {
                    "code": "PHILOSOPHY 101", 
                    "course_url": "http://www.chegg.com/courses/1586071/PHILOSOPHY/101", 
                    "name": "Introduction to Philosophy"
                }, 
                {
                    "code": "PHILOSOPHY 120", 
                    "course_url": "http://www.chegg.com/courses/1586071/PHILOSOPHY/120", 
                    "name": "Introduction to Ethics"
                }, 
                {
                    "code": "PHILOSOPHY 170", 
                    "course_url": "http://www.chegg.com/courses/1586071/PHILOSOPHY/170", 
                    "name": "Introduction to Logic"
                }
            ], 
            "name": "Philosophy", 
            "url": "http://www.chegg.com/courses/1586071/PHILOSOPHY"
        }, 
        {
            "abbr": "PHYSICAL EDUCATION", 
            "courses": [
                {
                    "code": "PHYSICAL EDUCATION 120", 
                    "course_url": "http://www.chegg.com/courses/1586071/PHYSICAL%20EDUCATION/120", 
                    "name": "Archery"
                }, 
                {
                    "code": "PHYSICAL EDUCATION 120-90", 
                    "course_url": "http://www.chegg.com/courses/1586071/PHYSICAL%20EDUCATION/120-90", 
                    "name": "Physical Education/ Wellness ?"
                }, 
                {
                    "code": "PHYSICAL EDUCATION 121", 
                    "course_url": "http://www.chegg.com/courses/1586071/PHYSICAL%20EDUCATION/121", 
                    "name": "Badminton"
                }, 
                {
                    "code": "PHYSICAL EDUCATION 122", 
                    "course_url": "http://www.chegg.com/courses/1586071/PHYSICAL%20EDUCATION/122", 
                    "name": "Basketball"
                }, 
                {
                    "code": "PHYSICAL EDUCATION 123", 
                    "course_url": "http://www.chegg.com/courses/1586071/PHYSICAL%20EDUCATION/123", 
                    "name": "Bowling"
                }, 
                {
                    "code": "PHYSICAL EDUCATION 126", 
                    "course_url": "http://www.chegg.com/courses/1586071/PHYSICAL%20EDUCATION/126", 
                    "name": "Fitness And Wellness"
                }, 
                {
                    "code": "PHYSICAL EDUCATION 127", 
                    "course_url": "http://www.chegg.com/courses/1586071/PHYSICAL%20EDUCATION/127", 
                    "name": "Golf"
                }, 
                {
                    "code": "PHYSICAL EDUCATION 132", 
                    "course_url": "http://www.chegg.com/courses/1586071/PHYSICAL%20EDUCATION/132", 
                    "name": "Karate"
                }, 
                {
                    "code": "PHYSICAL EDUCATION 135", 
                    "course_url": "http://www.chegg.com/courses/1586071/PHYSICAL%20EDUCATION/135", 
                    "name": "Racquetball"
                }, 
                {
                    "code": "PHYSICAL EDUCATION 139", 
                    "course_url": "http://www.chegg.com/courses/1586071/PHYSICAL%20EDUCATION/139", 
                    "name": "Self- Defense"
                }, 
                {
                    "code": "PHYSICAL EDUCATION 150", 
                    "course_url": "http://www.chegg.com/courses/1586071/PHYSICAL%20EDUCATION/150", 
                    "name": "Tennis"
                }, 
                {
                    "code": "PHYSICAL EDUCATION 151", 
                    "course_url": "http://www.chegg.com/courses/1586071/PHYSICAL%20EDUCATION/151", 
                    "name": "Volleyball"
                }, 
                {
                    "code": "PHYSICAL EDUCATION 211", 
                    "course_url": "http://www.chegg.com/courses/1586071/PHYSICAL%20EDUCATION/211", 
                    "name": "First Aid And Cpr"
                }
            ], 
            "name": "Physical Education", 
            "url": "http://www.chegg.com/courses/1586071/PHYSICAL%20EDUCATION"
        }, 
        {
            "abbr": "PHYSICS", 
            "courses": [
                {
                    "code": "PHYSICS 130", 
                    "course_url": "http://www.chegg.com/courses/1586071/PHYSICS/130", 
                    "name": "Descriptive Astronomy"
                }, 
                {
                    "code": "PHYSICS 131", 
                    "course_url": "http://www.chegg.com/courses/1586071/PHYSICS/131", 
                    "name": "Astronomy by Inquiry"
                }, 
                {
                    "code": "PHYSICS 133", 
                    "course_url": "http://www.chegg.com/courses/1586071/PHYSICS/133", 
                    "name": "Music, Sound, And Physics"
                }, 
                {
                    "code": "PHYSICS 137", 
                    "course_url": "http://www.chegg.com/courses/1586071/PHYSICS/137", 
                    "name": "Light"
                }, 
                {
                    "code": "PHYSICS 261", 
                    "course_url": "http://www.chegg.com/courses/1586071/PHYSICS/261", 
                    "name": "Physics For The Life Sciences I"
                }, 
                {
                    "code": "PHYSICS 262", 
                    "course_url": "http://www.chegg.com/courses/1586071/PHYSICS/262", 
                    "name": "Physics For The Life Sciences II"
                }, 
                {
                    "code": "PHYSICS 267 ,8", 
                    "course_url": "http://www.chegg.com/courses/1586071/PHYSICS/267%20%2C8", 
                    "name": "Life Sciences Physics Computations I, II"
                }, 
                {
                    "code": "PHYSICS 291", 
                    "course_url": "http://www.chegg.com/courses/1586071/PHYSICS/291", 
                    "name": "Elementary Classical Physics I"
                }, 
                {
                    "code": "PHYSICS 292", 
                    "course_url": "http://www.chegg.com/courses/1586071/PHYSICS/292", 
                    "name": "Elementary Classical Physics II"
                }, 
                {
                    "code": "PHYSICS 293 ,4", 
                    "course_url": "http://www.chegg.com/courses/1586071/PHYSICS/293%20%2C4", 
                    "name": "Physics Computations I, II"
                }
            ], 
            "name": "Physics", 
            "url": "http://www.chegg.com/courses/1586071/PHYSICS"
        }, 
        {
            "abbr": "POLITICAL SCIENCE", 
            "courses": [
                {
                    "code": "POLITICAL SCIENCE 100", 
                    "course_url": "http://www.chegg.com/courses/1586071/POLITICAL%20SCIENCE/100", 
                    "name": "Government And Politics in The United States"
                }, 
                {
                    "code": "POLITICAL SCIENCE 150", 
                    "course_url": "http://www.chegg.com/courses/1586071/POLITICAL%20SCIENCE/150", 
                    "name": "World Politics And Governments"
                }, 
                {
                    "code": "POLITICAL SCIENCE 210", 
                    "course_url": "http://www.chegg.com/courses/1586071/POLITICAL%20SCIENCE/210", 
                    "name": "State And Local Government And Politics"
                }
            ], 
            "name": "Political Science", 
            "url": "http://www.chegg.com/courses/1586071/POLITICAL%20SCIENCE"
        }, 
        {
            "abbr": "PSYCHOLOGY", 
            "courses": [
                {
                    "code": "PSYCHOLOGY 100", 
                    "course_url": "http://www.chegg.com/courses/1586071/PSYCHOLOGY/100", 
                    "name": "Introduction to Psychology"
                }, 
                {
                    "code": "PSYCHOLOGY 105", 
                    "course_url": "http://www.chegg.com/courses/1586071/PSYCHOLOGY/105", 
                    "name": "Professional And Career Issues in Psychology"
                }, 
                {
                    "code": "PSYCHOLOGY 230", 
                    "course_url": "http://www.chegg.com/courses/1586071/PSYCHOLOGY/230", 
                    "name": "Developmental Psychology"
                }
            ], 
            "name": "Psychology", 
            "url": "http://www.chegg.com/courses/1586071/PSYCHOLOGY"
        }, 
        {
            "abbr": "SOCIAL SERVICES TECHNOLOGY", 
            "courses": [
                {
                    "code": "SOCIAL SERVICES TECHNOLOGY 121", 
                    "course_url": "http://www.chegg.com/courses/1586071/SOCIAL%20SERVICES%20TECHNOLOGY/121", 
                    "name": "Social Service Techniques I"
                }, 
                {
                    "code": "SOCIAL SERVICES TECHNOLOGY 122", 
                    "course_url": "http://www.chegg.com/courses/1586071/SOCIAL%20SERVICES%20TECHNOLOGY/122", 
                    "name": "Social Service Techniques II"
                }, 
                {
                    "code": "SOCIAL SERVICES TECHNOLOGY 150", 
                    "course_url": "http://www.chegg.com/courses/1586071/SOCIAL%20SERVICES%20TECHNOLOGY/150", 
                    "name": "Introduction to Gerontological Services"
                }, 
                {
                    "code": "SOCIAL SERVICES TECHNOLOGY 171", 
                    "course_url": "http://www.chegg.com/courses/1586071/SOCIAL%20SERVICES%20TECHNOLOGY/171", 
                    "name": "Career Issues in Social Services I"
                }, 
                {
                    "code": "SOCIAL SERVICES TECHNOLOGY 172", 
                    "course_url": "http://www.chegg.com/courses/1586071/SOCIAL%20SERVICES%20TECHNOLOGY/172", 
                    "name": "Career Issues in Social Services II"
                }, 
                {
                    "code": "SOCIAL SERVICES TECHNOLOGY 223", 
                    "course_url": "http://www.chegg.com/courses/1586071/SOCIAL%20SERVICES%20TECHNOLOGY/223", 
                    "name": "Social Service Techniques III"
                }, 
                {
                    "code": "SOCIAL SERVICES TECHNOLOGY 251", 
                    "course_url": "http://www.chegg.com/courses/1586071/SOCIAL%20SERVICES%20TECHNOLOGY/251", 
                    "name": "Community Services For Senior Citizens"
                }, 
                {
                    "code": "SOCIAL SERVICES TECHNOLOGY 260", 
                    "course_url": "http://www.chegg.com/courses/1586071/SOCIAL%20SERVICES%20TECHNOLOGY/260", 
                    "name": "Introduction to Addiction"
                }, 
                {
                    "code": "SOCIAL SERVICES TECHNOLOGY 266", 
                    "course_url": "http://www.chegg.com/courses/1586071/SOCIAL%20SERVICES%20TECHNOLOGY/266", 
                    "name": "Social Service Techniques With Children And Families"
                }, 
                {
                    "code": "SOCIAL SERVICES TECHNOLOGY 273", 
                    "course_url": "http://www.chegg.com/courses/1586071/SOCIAL%20SERVICES%20TECHNOLOGY/273", 
                    "name": "Career Issues in Social Services III"
                }, 
                {
                    "code": "SOCIAL SERVICES TECHNOLOGY 275", 
                    "course_url": "http://www.chegg.com/courses/1586071/SOCIAL%20SERVICES%20TECHNOLOGY/275", 
                    "name": "Therapeutic Activities"
                }, 
                {
                    "code": "SOCIAL SERVICES TECHNOLOGY 276", 
                    "course_url": "http://www.chegg.com/courses/1586071/SOCIAL%20SERVICES%20TECHNOLOGY/276", 
                    "name": "Practicum in Therapeutic Activities"
                }, 
                {
                    "code": "SOCIAL SERVICES TECHNOLOGY 285", 
                    "course_url": "http://www.chegg.com/courses/1586071/SOCIAL%20SERVICES%20TECHNOLOGY/285", 
                    "name": "Social Services Practicum"
                }, 
                {
                    "code": "SOCIAL SERVICES TECHNOLOGY 287", 
                    "course_url": "http://www.chegg.com/courses/1586071/SOCIAL%20SERVICES%20TECHNOLOGY/287", 
                    "name": "Practicum in Therapeutic Activities And Long- Term Care"
                }, 
                {
                    "code": "SOCIAL SERVICES TECHNOLOGY 289", 
                    "course_url": "http://www.chegg.com/courses/1586071/SOCIAL%20SERVICES%20TECHNOLOGY/289", 
                    "name": "Practicum in Gerontologial Social Services"
                }, 
                {
                    "code": "SOCIAL SERVICES TECHNOLOGY 290", 
                    "course_url": "http://www.chegg.com/courses/1586071/SOCIAL%20SERVICES%20TECHNOLOGY/290", 
                    "name": "Special Topics: Community Services Technology"
                }, 
                {
                    "code": "SOCIAL SERVICES TECHNOLOGY 293", 
                    "course_url": "http://www.chegg.com/courses/1586071/SOCIAL%20SERVICES%20TECHNOLOGY/293", 
                    "name": "Field Work Orientation"
                }, 
                {
                    "code": "SOCIAL SERVICES TECHNOLOGY 294", 
                    "course_url": "http://www.chegg.com/courses/1586071/SOCIAL%20SERVICES%20TECHNOLOGY/294", 
                    "name": "Field Work Evaluation"
                }
            ], 
            "name": "", 
            "url": "http://www.chegg.com/courses/1586071/SOCIAL%20SERVICES%20TECHNOLOGY"
        }, 
        {
            "abbr": "SOCIAL STUDIES", 
            "courses": [
                {
                    "code": "SOCIAL STUDIES 240", 
                    "course_url": "http://www.chegg.com/courses/1586071/SOCIAL%20STUDIES/240", 
                    "name": "Human Relations"
                }, 
                {
                    "code": "SOCIAL STUDIES 241", 
                    "course_url": "http://www.chegg.com/courses/1586071/SOCIAL%20STUDIES/241", 
                    "name": "Technology And Human Values"
                }, 
                {
                    "code": "SOCIAL STUDIES 247", 
                    "course_url": "http://www.chegg.com/courses/1586071/SOCIAL%20STUDIES/247", 
                    "name": "Survey of Basic Economics"
                }, 
                {
                    "code": "SOCIAL STUDIES 251", 
                    "course_url": "http://www.chegg.com/courses/1586071/SOCIAL%20STUDIES/251", 
                    "name": "Human Behavior at Work"
                }, 
                {
                    "code": "SOCIAL STUDIES 256", 
                    "course_url": "http://www.chegg.com/courses/1586071/SOCIAL%20STUDIES/256", 
                    "name": "Diversity in American Society"
                }
            ], 
            "name": "", 
            "url": "http://www.chegg.com/courses/1586071/SOCIAL%20STUDIES"
        }, 
        {
            "abbr": "SOCIAL WORK", 
            "courses": [
                {
                    "code": "SOCIAL WORK 270", 
                    "course_url": "http://www.chegg.com/courses/1586071/SOCIAL%20WORK/270", 
                    "name": "Poverty And Minority Issues"
                }, 
                {
                    "code": "SOCIAL WORK 276", 
                    "course_url": "http://www.chegg.com/courses/1586071/SOCIAL%20WORK/276", 
                    "name": "Introduction to Social Welfare"
                }, 
                {
                    "code": "SOCIAL WORK 427", 
                    "course_url": "http://www.chegg.com/courses/1586071/SOCIAL%20WORK/427", 
                    "name": "Human Behavior & Social Environment I"
                }
            ], 
            "name": "", 
            "url": "http://www.chegg.com/courses/1586071/SOCIAL%20WORK"
        }, 
        {
            "abbr": "SOCIOLOGY", 
            "courses": [
                {
                    "code": "SOCIOLOGY 100", 
                    "course_url": "http://www.chegg.com/courses/1586071/SOCIOLOGY/100", 
                    "name": "Introduction to Sociology"
                }
            ], 
            "name": "Sociology", 
            "url": "http://www.chegg.com/courses/1586071/SOCIOLOGY"
        }, 
        {
            "abbr": "SPANISH", 
            "courses": [
                {
                    "code": "SPANISH 101 ,2", 
                    "course_url": "http://www.chegg.com/courses/1586071/SPANISH/101%20%2C2", 
                    "name": "Beginning Spanish I, II"
                }, 
                {
                    "code": "SPANISH 201 ,2", 
                    "course_url": "http://www.chegg.com/courses/1586071/SPANISH/201%20%2C2", 
                    "name": "Intermediate Spanish I, II"
                }
            ], 
            "name": "Spanish", 
            "url": "http://www.chegg.com/courses/1586071/SPANISH"
        }, 
        {
            "abbr": "SPECIAL EDUCATION", 
            "courses": [
                {
                    "code": "SPECIAL EDUCATION 225", 
                    "course_url": "http://www.chegg.com/courses/1586071/SPECIAL%20EDUCATION/225", 
                    "name": "Introduction to Exceptionalities"
                }, 
                {
                    "code": "SPECIAL EDUCATION 450", 
                    "course_url": "http://www.chegg.com/courses/1586071/SPECIAL%20EDUCATION/450", 
                    "name": "Special Education Programming: Early Childhood"
                }, 
                {
                    "code": "SPECIAL EDUCATION 459", 
                    "course_url": "http://www.chegg.com/courses/1586071/SPECIAL%20EDUCATION/459", 
                    "name": "Collaboration & Consultation in Schools And Community"
                }, 
                {
                    "code": "SPECIAL EDUCATION 467", 
                    "course_url": "http://www.chegg.com/courses/1586071/SPECIAL%20EDUCATION/467", 
                    "name": "Management Strategies in Special Education"
                }
            ], 
            "name": "", 
            "url": "http://www.chegg.com/courses/1586071/SPECIAL%20EDUCATION"
        }, 
        {
            "abbr": "STATISTICS", 
            "courses": [
                {
                    "code": "STATISTICS 250", 
                    "course_url": "http://www.chegg.com/courses/1586071/STATISTICS/250", 
                    "name": "Statistics For Everyday Life"
                }, 
                {
                    "code": "STATISTICS 260", 
                    "course_url": "http://www.chegg.com/courses/1586071/STATISTICS/260", 
                    "name": "Basic Statistics"
                }, 
                {
                    "code": "STATISTICS 261", 
                    "course_url": "http://www.chegg.com/courses/1586071/STATISTICS/261", 
                    "name": "Introductory Statistics I"
                }, 
                {
                    "code": "STATISTICS 262", 
                    "course_url": "http://www.chegg.com/courses/1586071/STATISTICS/262", 
                    "name": "Introductory Statistics II"
                }
            ], 
            "name": "", 
            "url": "http://www.chegg.com/courses/1586071/STATISTICS"
        }
    ], 
    "name": "1586071"
}